{
  "built_at": "2026-03-18T11:35:56.301121Z",
  "groups": {
    "Broad Market ETFs": [
      {
        "ticker": "NIFTYBEES",
        "daily": 0.85,
        "intra": 0.03,
        "5d": -0.42,
        "20d": -7.58,
        "atr_pct": 1.7,
        "dist_sma50_atr": -3.26,
        "rs": 100.0,
        "rs_chart": "data/charts/NIFTYBEES.png",
        "long": [],
        "short": [],
        "abc": "C"
      },
      {
        "ticker": "JUNIORBEES",
        "daily": 0.84,
        "intra": -0.04,
        "5d": -1.41,
        "20d": -5.96,
        "atr_pct": 2.5,
        "dist_sma50_atr": -1.59,
        "rs": 50.0,
        "rs_chart": "data/charts/JUNIORBEES.png",
        "long": [],
        "short": [],
        "abc": "C"
      },
      {
        "ticker": "MID150BEES",
        "daily": 1.75,
        "intra": 0.93,
        "5d": -0.74,
        "20d": -6.04,
        "atr_pct": 2.5,
        "dist_sma50_atr": -1.66,
        "rs": 85.0,
        "rs_chart": "data/charts/MID150BEES.png",
        "long": [],
        "short": [],
        "abc": "C"
      },
      {
        "ticker": "SMALLCAP",
        "daily": 1.88,
        "intra": 0.88,
        "5d": -1.33,
        "20d": null,
        "atr_pct": 2.3,
        "dist_sma50_atr": -2.0,
        "rs": 100.0,
        "rs_chart": "data/charts/SMALLCAP.png",
        "long": [],
        "short": [],
        "abc": "C"
      }
    ],
    "Sector ETFs": [
      {
        "ticker": "BANKBEES",
        "daily": 0.46,
        "intra": 0.34,
        "5d": -1.16,
        "20d": -9.79,
        "atr_pct": 1.9,
        "dist_sma50_atr": -3.59,
        "rs": 0.0,
        "rs_chart": "data/charts/BANKBEES.png",
        "long": [],
        "short": [],
        "abc": "C"
      },
      {
        "ticker": "ITBEES",
        "daily": 2.93,
        "intra": 3.16,
        "5d": -0.43,
        "20d": -10.77,
        "atr_pct": 3.8,
        "dist_sma50_atr": -3.66,
        "rs": 90.0,
        "rs_chart": "data/charts/ITBEES.png",
        "long": [],
        "short": [],
        "abc": "C"
      },
      {
        "ticker": "PHARMABEES",
        "daily": 0.0,
        "intra": -0.39,
        "5d": -3.29,
        "20d": 0.78,
        "atr_pct": 3.4,
        "dist_sma50_atr": 0.2,
        "rs": 100.0,
        "rs_chart": "data/charts/PHARMABEES.png",
        "long": [],
        "short": [],
        "abc": "A"
      },
      {
        "ticker": "AUTOBEES",
        "daily": 1.78,
        "intra": 4.39,
        "5d": -1.27,
        "20d": -9.14,
        "atr_pct": 3.3,
        "dist_sma50_atr": -1.92,
        "rs": 20.0,
        "rs_chart": "data/charts/AUTOBEES.png",
        "long": [],
        "short": [],
        "abc": "C"
      },
      {
        "ticker": "FMCGIETF",
        "daily": -0.06,
        "intra": -0.69,
        "5d": -1.96,
        "20d": -7.2,
        "atr_pct": 2.3,
        "dist_sma50_atr": -2.71,
        "rs": 100.0,
        "rs_chart": "data/charts/FMCGIETF.png",
        "long": [],
        "short": [],
        "abc": "C"
      },
      {
        "ticker": "INFRABEES",
        "daily": 1.21,
        "intra": 0.7,
        "5d": -0.72,
        "20d": -7.2,
        "atr_pct": 2.1,
        "dist_sma50_atr": -1.75,
        "rs": 20.0,
        "rs_chart": "data/charts/INFRABEES.png",
        "long": [],
        "short": [],
        "abc": "C"
      },
      {
        "ticker": "PSUBNKBEES",
        "daily": 0.71,
        "intra": 0.41,
        "5d": -2.01,
        "20d": -8.66,
        "atr_pct": 3.2,
        "dist_sma50_atr": -1.42,
        "rs": 15.0,
        "rs_chart": "data/charts/PSUBNKBEES.png",
        "long": [],
        "short": [],
        "abc": "C"
      },
      {
        "ticker": "CONSUMBEES",
        "daily": 0.84,
        "intra": -1.61,
        "5d": -0.15,
        "20d": -7.9,
        "atr_pct": 2.5,
        "dist_sma50_atr": -2.31,
        "rs": 100.0,
        "rs_chart": "data/charts/CONSUMBEES.png",
        "long": [],
        "short": [],
        "abc": "C"
      }
    ],
    "Commodity & Alternatives": [
      {
        "ticker": "GOLDBEES",
        "daily": -0.24,
        "intra": 0.02,
        "5d": -3.62,
        "20d": 2.67,
        "atr_pct": 3.5,
        "dist_sma50_atr": 0.23,
        "rs": 75.0,
        "rs_chart": "data/charts/GOLDBEES.png",
        "long": [],
        "short": [],
        "abc": "A"
      },
      {
        "ticker": "SILVERBEES",
        "daily": -1.56,
        "intra": 0.78,
        "5d": -5.78,
        "20d": 7.77,
        "atr_pct": 5.5,
        "dist_sma50_atr": -1.28,
        "rs": 10.0,
        "rs_chart": "data/charts/SILVERBEES.png",
        "long": [],
        "short": [],
        "abc": "C"
      },
      {
        "ticker": "LIQUIDBEES",
        "daily": 0.0,
        "intra": 0.1,
        "5d": 0.0,
        "20d": 0.0,
        "atr_pct": 0.1,
        "dist_sma50_atr": 0.01,
        "rs": 90.0,
        "rs_chart": "data/charts/LIQUIDBEES.png",
        "long": [],
        "short": [],
        "abc": "B"
      },
      {
        "ticker": "GILT5YBEES",
        "daily": 0.09,
        "intra": -0.06,
        "5d": -0.02,
        "20d": -0.05,
        "atr_pct": 0.9,
        "dist_sma50_atr": 0.58,
        "rs": 90.0,
        "rs_chart": "data/charts/GILT5YBEES.png",
        "long": [],
        "short": [],
        "abc": "A"
      },
      {
        "ticker": "CPSEETF",
        "daily": -0.18,
        "intra": -0.88,
        "5d": -0.77,
        "20d": 1.02,
        "atr_pct": 2.8,
        "dist_sma50_atr": 1.2,
        "rs": 70.0,
        "rs_chart": "data/charts/CPSEETF.png",
        "long": [],
        "short": [],
        "abc": "A"
      }
    ],
    "Global Context": [
      {
        "ticker": "MON100",
        "daily": 2.88,
        "intra": 2.04,
        "5d": 1.36,
        "20d": -1.55,
        "atr_pct": 2.9,
        "dist_sma50_atr": -0.58,
        "rs": 85.0,
        "rs_chart": "data/charts/MON100.png",
        "long": [],
        "short": [],
        "abc": "C"
      },
      {
        "ticker": "MASPTOP50",
        "daily": 2.03,
        "intra": 1.88,
        "5d": -0.85,
        "20d": null,
        "atr_pct": 2.6,
        "dist_sma50_atr": -0.9,
        "rs": 100.0,
        "rs_chart": "data/charts/MASPTOP50.png",
        "long": [],
        "short": [],
        "abc": "C"
      }
    ]
  },
  "column_ranges": {
    "Broad Market ETFs": {
      "daily": [
        0.84,
        1.88
      ],
      "intra": [
        -0.04,
        0.93
      ],
      "5d": [
        -1.41,
        -0.42
      ],
      "20d": [
        -7.58,
        -5.96
      ]
    },
    "Sector ETFs": {
      "daily": [
        -0.06,
        2.93
      ],
      "intra": [
        -1.61,
        4.39
      ],
      "5d": [
        -3.29,
        -0.15
      ],
      "20d": [
        -10.77,
        0.78
      ]
    },
    "Commodity & Alternatives": {
      "daily": [
        -1.56,
        0.09
      ],
      "intra": [
        -0.88,
        0.78
      ],
      "5d": [
        -5.78,
        0.0
      ],
      "20d": [
        -0.05,
        7.77
      ]
    },
    "Global Context": {
      "daily": [
        2.03,
        2.88
      ],
      "intra": [
        1.88,
        2.04
      ],
      "5d": [
        -0.85,
        1.36
      ],
      "20d": [
        -1.55,
        -1.55
      ]
    }
  }
}